url2md4ai/__init__.py
url2md4ai/cli.py
url2md4ai/config.py
url2md4ai/converter.py
url2md4ai/utils/__init__.py
url2md4ai/utils/logger.py
url2md4ai/utils/rate_limiter.py
url2md4ai-0.1.2.dist-info/METADATA
url2md4ai-0.1.2.dist-info/WHEEL
url2md4ai-0.1.2.dist-info/entry_points.txt
url2md4ai-0.1.2.dist-info/licenses/LICENSE
url2md4ai-0.1.2.dist-info/RECORD
