Metadata-Version: 2.4
Name: url2md4ai
Version: 0.1.2
Summary: 🚀 Lean Python tool for extracting clean, LLM-optimized markdown from web pages. Handles dynamic content with Playwright + Trafilatura for maximum information extraction efficiency.
Project-URL: Homepage, https://github.com/mazzasaverio/url2md4ai
Project-URL: Repository, https://github.com/mazzasaverio/url2md4ai
Project-URL: Documentation, https://github.com/mazzasaverio/url2md4ai#readme
Project-URL: Bug Tracker, https://github.com/mazzasaverio/url2md4ai/issues
Project-URL: Changelog, https://github.com/mazzasaverio/url2md4ai/blob/main/CHANGELOG.md
Project-URL: Source Code, https://github.com/mazzasaverio/url2md4ai
Author-email: Saverio Mazza <saverio3107@gmail.com>
Maintainer-email: Saverio Mazza <saverio3107@gmail.com>
License: MIT
License-File: LICENSE
Keywords: ai-preprocessing,content-extraction,dynamic-rendering,html-to-markdown,information-extraction,javascript-rendering,lean,llm,llm-optimization,markdown,playwright,text-extraction,trafilatura,url,web-automation,web-scraping
Classifier: Development Status :: 4 - Beta
Classifier: Intended Audience :: Developers
Classifier: Intended Audience :: Science/Research
Classifier: License :: OSI Approved :: MIT License
Classifier: Operating System :: OS Independent
Classifier: Programming Language :: Python :: 3
Classifier: Programming Language :: Python :: 3.10
Classifier: Programming Language :: Python :: 3.11
Classifier: Programming Language :: Python :: 3.12
Classifier: Programming Language :: Python :: 3.13
Classifier: Topic :: Internet :: WWW/HTTP
Classifier: Topic :: Software Development :: Libraries :: Python Modules
Classifier: Topic :: Text Processing :: Markup :: HTML
Classifier: Topic :: Text Processing :: Markup :: Markdown
Classifier: Topic :: Utilities
Requires-Python: >=3.10
Requires-Dist: aiohttp>=3.9.0
Requires-Dist: beautifulsoup4>=4.12.0
Requires-Dist: click>=8.1.7
Requires-Dist: html2text>=2024.2.26
Requires-Dist: loguru>=0.7.2
Requires-Dist: lxml>=5.0.0
Requires-Dist: openai>=1.93.0
Requires-Dist: pandas>=2.3.0
Requires-Dist: playwright>=1.40.0
Requires-Dist: python-dotenv>=1.0.0
Requires-Dist: tabulate>=0.9.0
Requires-Dist: trafilatura>=1.6.1
Provides-Extra: dev
Requires-Dist: black>=24.0.0; extra == 'dev'
Requires-Dist: ipykernel>=6.25.0; extra == 'dev'
Requires-Dist: jupyter>=1.0.0; extra == 'dev'
Requires-Dist: mypy>=1.13.0; extra == 'dev'
Requires-Dist: pre-commit>=4.0.0; extra == 'dev'
Requires-Dist: pytest-asyncio>=0.23.0; extra == 'dev'
Requires-Dist: pytest-cov>=4.0.0; extra == 'dev'
Requires-Dist: pytest-mock>=3.12.0; extra == 'dev'
Requires-Dist: pytest>=8.0.0; extra == 'dev'
Requires-Dist: ruff>=0.8.0; extra == 'dev'
